espnet_model_zoo/__init__.py
espnet_model_zoo/downloader.py
espnet_model_zoo/table.csv
espnet_model_zoo/zenodo_upload.py
espnet_model_zoo-0.1.7.dist-info/LICENSE
espnet_model_zoo-0.1.7.dist-info/METADATA
espnet_model_zoo-0.1.7.dist-info/WHEEL
espnet_model_zoo-0.1.7.dist-info/entry_points.txt
espnet_model_zoo-0.1.7.dist-info/top_level.txt
espnet_model_zoo-0.1.7.dist-info/RECORD
