Metadata-Version: 2.1
Name: espnet-model-zoo
Version: 0.1.7
Summary: ESPnet Model Zoo
Home-page: http://github.com/espnet/espnet_model_zoo
License: Apache Software License
Platform: UNKNOWN
Classifier: Programming Language :: Python
Classifier: Programming Language :: Python :: 3
Classifier: Programming Language :: Python :: 3.6
Classifier: Programming Language :: Python :: 3.7
Classifier: Programming Language :: Python :: 3.8
Classifier: Programming Language :: Python :: 3.9
Classifier: Development Status :: 5 - Production/Stable
Classifier: Intended Audience :: Science/Research
Classifier: Operating System :: POSIX :: Linux
Classifier: License :: OSI Approved :: Apache Software License
Classifier: Topic :: Software Development :: Libraries :: Python Modules
Requires-Python: >=3.6.0
Requires-Dist: pandas
Requires-Dist: requests
Requires-Dist: tqdm
Requires-Dist: numpy
Requires-Dist: espnet
Requires-Dist: huggingface-hub
Requires-Dist: filelock
Provides-Extra: test
Requires-Dist: pytest (>=3.3.0) ; extra == 'test'
Requires-Dist: pytest-pythonpath (>=0.7.3) ; extra == 'test'
Requires-Dist: pytest-cov (>=2.7.1) ; extra == 'test'
Requires-Dist: hacking (>=1.1.0) ; extra == 'test'
Requires-Dist: mock (>=2.0.0) ; extra == 'test'
Requires-Dist: pycodestyle ; extra == 'test'
Requires-Dist: flake8 (>=3.7.8) ; extra == 'test'
Requires-Dist: black ; extra == 'test'
